MANIFEST.in
README.rst
bottle_boilerplate.py
requirements.txt
setup.py
bottle_boilerplate.egg-info/PKG-INFO
bottle_boilerplate.egg-info/SOURCES.txt
bottle_boilerplate.egg-info/dependency_links.txt
bottle_boilerplate.egg-info/entry_points.txt
bottle_boilerplate.egg-info/not-zip-safe
bottle_boilerplate.egg-info/requires.txt
bottle_boilerplate.egg-info/top_level.txt